{"name":"Private-board","tagline":"Private Board est un site web open source permettant le tri automatique, le rangement et la lecture de fichiers sur son serveur. Nous ne sommes en aucun cas responsables des fichiers que vous hébergez sur votre serveur. ","body":"### Private Board\r\nPrivate Board est un site web open source permettant le tri automatique, le rangement et la lecture de fichiers sur son serveur. Nous ne sommes en aucun cas responsables des fichiers que vous hébergez sur votre serveur.\r\n\r\n### Designer Templates\r\n![02](https://s.gks.gs/img/img/09-2013/Design_privateboard.jpg)\r\n![01](https://s.gks.gs/img/img/11-2013/1739147325iPad_iPhone_MacBook_Pro1.png)\r\n\r\n### Authors and Contributors\r\nPierre - http://yourcreation.fr\r\n\r\n","google":"","note":"Don't delete this file! It's used internally to help with page regeneration."}